{
  "tasks": [
    {
      "title": "<p>Kerja sama dengan Shanty +6260</p>",
      "category": "tab_1758689294005",
      "priority": "medium",
      "completed": false,
      "createdAt": "2025-09-30T06:33:56.468Z",
      "id": 1759214036468
    },
    {
      "title": "<p>Jubah brunai +6738119912</p><p><br></p><p>Cek Paket LA</p>",
      "category": "tab_1758689294005",
      "priority": "medium",
      "completed": false,
      "createdAt": "2025-09-30T06:34:17.601Z",
      "id": 1759213535477
    },
    {
      "title": "<p>Aby Ruham +0204</p><p><br></p><p>tanya tanya Paket 20jt an</p><p><br></p>",
      "category": "tab_1758689294005",
      "priority": "medium",
      "completed": false,
      "createdAt": "2025-09-30T06:25:04.829Z",
      "id": 1759213504829
    },
    {
      "title": "<p>Deni +4164</p><p><br></p><p>visa Sama hotel</p><p><br></p><p>berangkat tanggal 18 november - 1 Desember</p><p><br></p><p>makkah 19 - 27</p><p>madinah 27 -1</p>",
      "category": "tab_1758689294005",
      "priority": "medium",
      "completed": false,
      "createdAt": "2025-09-30T06:24:12.390Z",
      "id": 1759213399599
    },
    {
      "title": "<p>Catat Jadwal Gaji</p>",
      "category": "work",
      "priority": "high",
      "completed": false,
      "createdAt": "2025-09-30T06:21:22.676Z",
      "id": 1759213263172
    },
    {
      "title": "<p>Jadwal brosur yang Di upload</p>",
      "category": "work",
      "priority": "medium",
      "completed": false,
      "createdAt": "2025-09-30T05:55:08.115Z",
      "id": 1759211708115
    },
    {
      "title": "<p>Buat Online webinner untuk Umroh</p>",
      "category": "tab_1758689294005",
      "priority": "medium",
      "completed": false,
      "createdAt": "2025-09-25T05:30:16.633Z",
      "id": 1758778216633
    },
    {
      "title": "<ol><li>Brosur Sudah selesai</li><li>Di Upload Di google drive = 5</li><li>Facbook</li></ol><p><br></p><ol><li>badal Umroh</li><li>sertifikat </li><li>muthowif </li><li>Tiket Kereta Cepat V</li><li>Group WA</li><li><br></li></ol><p><br></p>",
      "category": "work",
      "priority": "medium",
      "completed": true,
      "createdAt": "2025-09-30T05:56:50.085Z",
      "id": 1758778192766
    },
    {
      "title": "<p>Tambahkan Group Ke whatsapp untu marketing</p>",
      "category": "tab_1758689294005",
      "priority": "medium",
      "completed": true,
      "createdAt": "2025-09-25T05:05:45.753Z",
      "id": 1758776745753
    },
    {
      "title": "<ol><li>Jam 7 kerja sampai jam 10 Siang</li><li>hari minggu libur musyawaroh</li><li><br></li></ol><p>Laporan musyawaroh</p><p>Berapa orang group</p><p>Laporan musyawaroh</p><p>Berapa orang group</p><p>Upload Brosur </p><ol><li>Facebook</li><li>Instagram</li><li>Group wa albary haramain</li><li>group Wa pasar</li></ol><p>Apa Aja yang Di upload</p><p>Upload Brosur </p><ol><li>Facebook</li><li>Instagram</li><li>Group wa albary haramain</li><li>group Wa pasar</li></ol><p><br></p><p>Apa Aja yang Di upload</p><p><br></p><p><br></p><p>Agenda </p><ol><li>Agenda Jadwal V selesai</li><li> rencan penjagaan pelanggan lama dan cari pelanggan bar</li><li>buat sapa sapaan</li><li>Pembelajaran di buraq</li><li><br></li></ol><p>agenda jamal memasukkan ke group yang ada chat</p>",
      "category": "work",
      "priority": "medium",
      "completed": false,
      "createdAt": "2025-10-02T07:53:42.111Z",
      "id": 1758695686662
    }
  ],
  "tabs": [
    {
      "id": "all",
      "name": "Semua",
      "icon": "fa-list"
    },
    {
      "id": "work",
      "name": "Kerja",
      "icon": "fa-briefcase"
    },
    {
      "id": "personal",
      "name": "Pribadi",
      "icon": "fa-user"
    },
    {
      "id": "study",
      "name": "Belajar",
      "icon": "fa-book"
    },
    {
      "id": "health",
      "name": "Kesehatan",
      "icon": "fa-heartbeat"
    },
    {
      "id": "tab_1758689294005",
      "name": "Albary Haramain",
      "icon": "fa-star"
    }
  ]
}