{
  "albary_pengguna": [
    {
      "nama": "Pengguna 1",
      "kantong": [
        {
          "nama": "Kas Rumah",
          "saldo": 500000,
          "mataUang": "Rp"
        },
        {
          "nama": "Tabungan SAR",
          "saldo": 300,
          "mataUang": "SAR"
        }
      ],
      "transaksi": []
    },
    {
      "nama": "jamaluddin",
      "kantong": [
        {
          "nama": "20%",
          "saldo": 10,
          "mataUang": "SAR"
        }
      ],
      "transaksi": [
        {
          "id": "1757466916724212",
          "kantong": 0,
          "jenis": "masuk",
          "jumlah": 10,
          "mataUang": "SAR",
          "keterangan": "makan",
          "tanggal": "2025-09-10"
        }
      ]
    }
  ],
  "albary_user_terakhir": "1",
  "albary_kantong_terakhir": "0"
}